csvtickerlist/__init__.py
csvtickerlist-0.0.2.dist-info/METADATA
csvtickerlist-0.0.2.dist-info/WHEEL
csvtickerlist-0.0.2.dist-info/top_level.txt
csvtickerlist-0.0.2.dist-info/RECORD
