Metadata-Version: 2.1
Name: csvtickerlist
Version: 0.0.2
Summary: Generate a CSV of all current tickers
Author: Christian K.
Author-email: <christiank1inquiries@gmail.com>
Keywords: python,stocks,tickers,algo-trading,finance
Classifier: Development Status :: 1 - Planning
Classifier: Intended Audience :: Developers
Classifier: Programming Language :: Python :: 3
Classifier: Operating System :: Unix
Classifier: Operating System :: MacOS :: MacOS X
Classifier: Operating System :: Microsoft :: Windows
Requires-Dist: selenium
